pin_how_poem/__init__.py
pin_how_poem/bank.txt
pin_how_poem/roll.py
pin_how_poem-0.0.1.dist-info/METADATA
pin_how_poem-0.0.1.dist-info/WHEEL
pin_how_poem-0.0.1.dist-info/top_level.txt
pin_how_poem-0.0.1.dist-info/RECORD
