Metadata-Version: 2.4
Name: pin-how-poem
Version: 0.0.1
Summary: Use Chinese word dices to generate contrasting sentences. A poetry teaching aid designed by lyy0323 from Guoxue Club, SJTU.
Author: lyy0323
Project-URL: Homepage, https://github.com/lyy0323/
Project-URL: Bug Tracker, https://github.com/lyy0323/issues
Classifier: Programming Language :: Python :: 3
Classifier: Operating System :: OS Independent
Requires-Python: >=3.6
